nycparks/.gitignore
nycparks/__init__.py
nycparks/data/court_info_and_availability_is_saved_here.txt
nycparks/main.py
"nycparks/utils/__init__,py"
nycparks/utils/reserver.py
nycparks/utils/texter.py
nycparks/utils/times.py
nycparks-0.1.0.dist-info/entry_points.txt
nycparks-0.1.0.dist-info/WHEEL
nycparks-0.1.0.dist-info/METADATA
nycparks-0.1.0.dist-info/RECORD
