Metadata-Version: 2.1
Name: nycparks
Version: 0.1.0
Summary: 
Author: Austin Botelho
Author-email: austinbotelho@nyu.edu
Requires-Python: >=3.8,<4.0
Classifier: Programming Language :: Python :: 3
Classifier: Programming Language :: Python :: 3.8
Classifier: Programming Language :: Python :: 3.9
Classifier: Programming Language :: Python :: 3.10
Classifier: Programming Language :: Python :: 3.11
Requires-Dist: bs4 (>=0.0.1,<0.0.2)
Requires-Dist: click (>=8.1.6,<9.0.0)
Requires-Dist: html5lib (>=1.1,<2.0)
Requires-Dist: lxml (>=4.9.3,<5.0.0)
Requires-Dist: pandas (>=2.0.3,<3.0.0)
Requires-Dist: pynput (>=1.7.6,<2.0.0)
Requires-Dist: pywhatkit (>=5.4,<6.0)
Requires-Dist: selenium (>=4.11.2,<5.0.0)
Requires-Dist: webdriver-manager (>=4.0.0,<5.0.0)
